CHANGES.txt
LICENSE.txt
MANIFEST.in
README.md
setup.py
js/__init__.py
js.lodash.egg-info/PKG-INFO
js.lodash.egg-info/SOURCES.txt
js.lodash.egg-info/dependency_links.txt
js.lodash.egg-info/entry_points.txt
js.lodash.egg-info/namespace_packages.txt
js.lodash.egg-info/not-zip-safe
js.lodash.egg-info/requires.txt
js.lodash.egg-info/top_level.txt
js/lodash/__init__.py
js/lodash/test_lodash.txt
js/lodash/resources/js/lodash.core.js
js/lodash/resources/js/lodash.core.min.js
js/lodash/resources/js/lodash.js
js/lodash/resources/js/lodash.min.js