Metadata-Version: 1.0
Name: js.lodash
Version: 4.17.4
Summary: Fanstatic packaging of lodash
Home-page: UNKNOWN
Author: Fanstatic Developers
Author-email: fanstatic@googlegroups.com
License: BSD
Platform: UNKNOWN
